mfa_decoder/__init__.py
mfa_decoder/mfa_decoder.py
mfa_decoder-1.0.6.dist-info/LICENSE
mfa_decoder-1.0.6.dist-info/METADATA
mfa_decoder-1.0.6.dist-info/WHEEL
mfa_decoder-1.0.6.dist-info/entry_points.txt
mfa_decoder-1.0.6.dist-info/top_level.txt
mfa_decoder-1.0.6.dist-info/RECORD
