Metadata-Version: 2.1
Name: mfa-decoder
Version: 1.0.6
Summary: Decode QR Code & Generate TOTP
Home-page: https://www.nghiahl.cloud
Author: Nghia Handsome
Author-email: nghiahandsome@gmail.com
License: GNU General Public License v3 (GPLv3)
Keywords: QR_Code TOTP 2FA Secret-Code MFA OTP
Classifier: Programming Language :: Python :: 3
Classifier: License :: OSI Approved :: GNU General Public License v3 (GPLv3)
Classifier: Operating System :: OS Independent
License-File: LICENSE
Requires-Dist: opencv-python
Requires-Dist: pyzbar
Requires-Dist: pyotp
